mpcorbget/__init__.py
mpcorbget/__main__.py
mpcorbget/mpcorbget.py
mpcorbget-1.0.0a7.dist-info/DESCRIPTION.rst
mpcorbget-1.0.0a7.dist-info/METADATA
mpcorbget-1.0.0a7.dist-info/RECORD
mpcorbget-1.0.0a7.dist-info/WHEEL
mpcorbget-1.0.0a7.dist-info/entry_points.txt
mpcorbget-1.0.0a7.dist-info/metadata.json
mpcorbget-1.0.0a7.dist-info/top_level.txt
