Metadata-Version: 2.0
Name: mpcorbget
Version: 1.0.0a7
Summary: A tool for observing minor planets
Home-page: https://github.com/davenporta/mpcorbget
Author: Alexander Davenport
Author-email: alexhdavenport@gmail.com
License: MIT
Keywords: astronomy ephemeris ephem minorplanets research
Platform: UNKNOWN
Classifier: Development Status :: 3 - Alpha
Classifier: Intended Audience :: Science/Research
Classifier: Topic :: Scientific/Engineering :: Astronomy
Classifier: License :: OSI Approved :: MIT License
Classifier: Programming Language :: Python :: 3.5
Requires-Dist: ephem
Requires-Dist: future
Requires-Dist: requests
